LICENSE
README.rst
setup.cfg
setup.py
signnow_python_sdk/__init__.py
signnow_python_sdk/config.py
signnow_python_sdk/document.py
signnow_python_sdk/folder.py
signnow_python_sdk/link.py
signnow_python_sdk/oauth2token.py
signnow_python_sdk/template.py
signnow_python_sdk/user.py
signnow_python_sdk/webhook.py
signnow_python_sdk.egg-info/PKG-INFO
signnow_python_sdk.egg-info/SOURCES.txt
signnow_python_sdk.egg-info/dependency_links.txt
signnow_python_sdk.egg-info/not-zip-safe
signnow_python_sdk.egg-info/requires.txt
signnow_python_sdk.egg-info/top_level.txt