Metadata-Version: 1.2
Name: signnow-python-sdk
Version: 2.0
Summary: Python SDK for the SignNow system
Home-page: https://github.com/signnow/SNPythonSDK
Author: SignNow
Author-email: api@signnow.com
License: Apache 2.0
Download-URL: https://github.com/signnow/SNPythonSDK/archive/refs/tags/2.0.tar.gz
Platform: UNKNOWN
Classifier: Programming Language :: Python :: 3
Classifier: License :: OSI Approved :: Apache Software License
Classifier: Operating System :: OS Independent
Requires-Python: >=3.6
